LICENSE
MANIFEST.in
README.rst
setup.py
geradorstr/__init__.py
geradorstr/__main__.py
geradorstr/funcoesauxiliares.py
geradorstr/geradorstr.py
geradorstr/metainfo.py
geradorstr/parse.py
geradorstr.egg-info/PKG-INFO
geradorstr.egg-info/SOURCES.txt
geradorstr.egg-info/dependency_links.txt
geradorstr.egg-info/entry_points.txt
geradorstr.egg-info/top_level.txt