Metadata-Version: 1.1
Name: geradorstr
Version: 0.1.0
Summary: Generate smarts string
Home-page: https://github.com/alexaleluia12/geradorstr
Author: Alex Aleluia
Author-email: alexaleluiaforgit@gmail.com
License: MIT
Platform: UNKNOWN
Classifier: Development Status :: 4 - Beta
Classifier: Environment :: Console
Classifier: Intended Audience :: Developers
Classifier: Intended Audience :: Science/Research
Classifier: License :: OSI Approved :: MIT License
Classifier: Operating System :: OS Independent
Classifier: Programming Language :: Python
Classifier: Programming Language :: Python :: 3
Classifier: Programming Language :: Python :: 3.4
Classifier: Programming Language :: Python :: 3.5
Classifier: Natural Language :: Portuguese (Brazilian)
Classifier: Topic :: Software Development :: Build Tools
